evanlib/__init__.py
evanlib/kucoin.py
kcevan-1.4.dist-info/METADATA
kcevan-1.4.dist-info/WHEEL
kcevan-1.4.dist-info/top_level.txt
kcevan-1.4.dist-info/RECORD
