Metadata-Version: 2.1
Name: kcevan
Version: 1.4
Summary: evan's private utils.
License: MIT Licence
Keywords: pip,kcevan
Platform: any
Requires-Dist: docopt
Requires-Dist: hdfs
Requires-Dist: livy
